glampy/__init__.py
glampy/io.py
glampy/logging.py
glampy/style.py
glampy-0.4.2.dist-info/METADATA
glampy-0.4.2.dist-info/WHEEL
glampy-0.4.2.dist-info/RECORD
