Metadata-Version: 2.4
Name: glampy
Version: 0.4.2
Summary: Make your python CLI prints and logs simple but glamorous
License: MIT
Keywords: cli,logging,styling,terminal
Author: snaeil
Author-email: schnegel@posteo.de
Requires-Python: >=3.11,<4.0
Classifier: Development Status :: 5 - Production/Stable
Classifier: Environment :: Console
Classifier: Intended Audience :: Developers
Classifier: License :: OSI Approved :: MIT License
Classifier: Operating System :: MacOS
Classifier: Operating System :: Microsoft :: Windows
Classifier: Operating System :: POSIX :: Linux
Classifier: Programming Language :: Python :: 3
Classifier: Programming Language :: Python :: 3.11
Classifier: Programming Language :: Python :: 3.12
Classifier: Programming Language :: Python :: 3.13
Classifier: Programming Language :: Python :: 3.14
Classifier: Programming Language :: Python :: 3.10
Classifier: Typing :: Typed
Project-URL: Bug Tracker, https://github.com/snaeil/glampy/issues
Project-URL: Homepage, https://github.com/snaeil/glampy
Project-URL: Repository, https://github.com/snaeil/glampy
